{
  "type": "FeatureCollection",
  "_note": "Generic fallback intersections. The live demo corridor lives in data/scenario.py; these keep the standalone module demos runnable with zero network.",
  "features": [
    {
      "type": "Feature",
      "properties": {
        "id": "somerville-park-tight",
        "name": "Somerville Ave & Park St (Tight Corner)",
        "description": "Narrow curb return — historically difficult for fire apparatus / semis",
        "lon": -71.1050, "lat": 42.3805,
        "corner_radius_ft": 12,
        "road_width_ft": 26,
        "turn_angle_deg": 90,
        "pci": 58,
        "obstacles": [{"type": "traffic_signal_pole", "lon": -71.10498, "lat": 42.38052}]
      },
      "geometry": {"type": "Point", "coordinates": [-71.1050, 42.3805]}
    },
    {
      "type": "Feature",
      "properties": {
        "id": "somerville-holland-broadway",
        "name": "Holland St & Broadway (Davis Square)",
        "description": "Moderate corner — standard bus route",
        "lon": -71.1215, "lat": 42.3967,
        "corner_radius_ft": 25,
        "road_width_ft": 30,
        "turn_angle_deg": 90,
        "pci": 81,
        "obstacles": []
      },
      "geometry": {"type": "Point", "coordinates": [-71.1215, 42.3967]}
    },
    {
      "type": "Feature",
      "properties": {
        "id": "somerville-mcgrath-washington",
        "name": "McGrath Hwy & Washington St",
        "description": "Wide arterial — large curb radius, clear of obstructions",
        "lon": -71.0946, "lat": 42.3818,
        "corner_radius_ft": 35,
        "road_width_ft": 44,
        "turn_angle_deg": 90,
        "pci": 72,
        "obstacles": []
      },
      "geometry": {"type": "Point", "coordinates": [-71.0946, 42.3818]}
    }
  ]
}
